grvpn/__init__.py
grvpn/auth.py
grvpn/main.py
grvpn/openvpn.py
grvpn/static/success.html
grvpn/sudo_manager.py
grvpn/vpn.py
grvpn-1.5.0.dist-info/METADATA
grvpn-1.5.0.dist-info/WHEEL
grvpn-1.5.0.dist-info/entry_points.txt
grvpn-1.5.0.dist-info/RECORD
