Metadata-Version: 2.3
Name: grvpn
Version: 1.5.0
Summary: Gaucho Racing's custom VPN manager and client, built on top of OpenVPN.
Author: Bharat Kathi
Author-email: bharat1031@gmail.com
Requires-Python: >=3.12
Classifier: Programming Language :: Python :: 3
Classifier: Programming Language :: Python :: 3.12
Classifier: Programming Language :: Python :: 3.13
Requires-Dist: psutil (>=7.0.0,<8.0.0)
Requires-Dist: requests (>=2.32.4,<3.0.0)
Requires-Dist: rich (>=14.1.0,<15.0.0)
Requires-Dist: typer (>=0.16.0,<0.17.0)
Requires-Dist: typing-extensions (>=4.14.1,<5.0.0)
